variable_lib_drturtle/__init__.py
variable_lib_drturtle/arrays.py
variable_lib_drturtle/earth.py
variable_lib_drturtle/forces.py
variable_lib_drturtle/resource.py
variable_lib_drturtle/simul.py
variable_lib_drturtle/utils.py
variable_lib_drturtle/variables.py
variable_lib_drturtle-0.5.7.dist-info/METADATA
variable_lib_drturtle-0.5.7.dist-info/WHEEL
variable_lib_drturtle-0.5.7.dist-info/licenses/LICENSE
variable_lib_drturtle-0.5.7.dist-info/RECORD
